AUTHORS.txt
CHANGELOG.txt
LICENSE.txt
MANIFEST.in
README.rst
make_docs.sh
requirements.txt
requirements_doc.txt
requirements_py2.txt
requirements_py3.txt
requirements_test.txt
runtests.py
setup.cfg
setup.py
tox.ini
demos/api_pulse.py
demos/noise.py
demos/scan_wunderbars.py
docs/.DS_Store
docs/manual/.DS_Store
docs/manual/Makefile
docs/manual/classes.txt
docs/manual/conf.py
docs/manual/contributing.txt
docs/manual/documentation.txt
docs/manual/examples.txt
docs/manual/index.txt
docs/manual/installing.txt
docs/manual/make.bat
docs/manual/raspberrypi.txt
docs/manual/testing.txt
docs/manual/_static/.gitignore
docs/manual/_templates/.gitignore
relayr/__init__.py
relayr/api.py
relayr/ble.py
relayr/client.py
relayr/compat.py
relayr/config.py
relayr/dataconnection.py
relayr/exceptions.py
relayr/resources.py
relayr/version.py
relayr.egg-info/PKG-INFO
relayr.egg-info/SOURCES.txt
relayr.egg-info/dependency_links.txt
relayr.egg-info/not-zip-safe
relayr.egg-info/requires.txt
relayr.egg-info/top_level.txt
relayr/utils/__init__.py
relayr/utils/terminalsize.py
relayr/utils/workarounds.py
tests/.DS_Store
tests/__init__.py
tests/conftest.py
tests/fixture_anonymous.py
tests/fixture_registered.py
tests/test_anonymous.py
tests/test_bluetooth.py
tests/test_config.py
tests/test_data_access.py
tests/test_registered.py